fastapi_project/__init__.py
fastapi_project/__main__.py
fastapi_project/components/generate_folders.py
fastapi_project/config.py
fastapi_project/manage.py
fastapi_project-0.1.0.dist-info/entry_points.txt
fastapi_project-0.1.0.dist-info/WHEEL
fastapi_project-0.1.0.dist-info/METADATA
fastapi_project-0.1.0.dist-info/RECORD
